{"stats":{"minecraft:custom":{"minecraft:sprint_one_cm":160,"minecraft:time_since_rest":211130,"minecraft:walk_one_cm":1702,"minecraft:total_world_time":640976,"minecraft:leave_game":4,"minecraft:fly_one_cm":103930,"minecraft:crouch_one_cm":449,"minecraft:sneak_time":1668,"minecraft:play_time":211130,"minecraft:jump":23,"minecraft:time_since_death":211130},"minecraft:used":{"minecraft:stone":30,"minecraft:comparator":1,"minecraft:repeater":2,"minecraft:oak_button":1,"minecraft:stone_button":2,"minecraft:redstone":11,"minecraft:command_block":3}},"DataVersion":4325}